{
	"format_version": "1.21.6",
	"credit": "Made with Blockbench",
	"texture_size": [225, 950],
	"textures": {
		"0": "yte:block/hitachi_ghl820",
		"particle": "yte:block/hitachi_ghl820"
	},
	"elements": [
		{
			"from": [0, 5.1, 0],
			"to": [1.25, 11.135, 0.45],
			"rotation": {"angle": 0, "axis": "y", "origin": [-8.125, 2.225, 0]},
			"faces": {
				"north": {"uv": [0, 1.43459, 12.76429, 6.33308], "texture": "#0"},
				"east": {"uv": [12.44444, 0, 16, 16], "texture": "#0"},
				"south": {"uv": [8, 0.84211, 12.44444, 15.15789], "texture": "#0"}
			}
		},
		{
			"from": [0, 11.175, 1.4215],
			"to": [1.25, 11.225, 1.5465],
			"rotation": {"angle": -22.5, "axis": "x", "origin": [-8.125, 8.4, 1.1]},
			"faces": {
				"east": {"uv": [12.44444, 0, 16, 0.84211], "texture": "#0"},
				"south": {"uv": [8, 0, 12.44444, 0.84211], "texture": "#0"}
			}
		},
		{
			"from": [0, 11.675, 2.4],
			"to": [1.25, 11.725, 2.525],
			"rotation": {"angle": -45, "axis": "x", "origin": [-8.125, 8.9, 2.075]},
			"faces": {
				"east": {"uv": [12.44444, 0, 16, 0.84211], "texture": "#0"},
				"south": {"uv": [8, 0, 12.44444, 0.84211], "texture": "#0"}
			}
		},
		{
			"from": [0, 10.0575, -0.04],
			"to": [1.25, 10.1825, 0.01],
			"rotation": {"angle": 22.5, "axis": "x", "origin": [-8.125, 9.725, 2.8]},
			"faces": {
				"east": {"uv": [12.44444, 0, 16, 0.84211], "texture": "#0"},
				"up": {"uv": [8, 0, 12.44444, 0.84211], "texture": "#0"}
			}
		},
		{
			"from": [0, 3.9135, 0.4],
			"to": [1.25, 4.0385, 0.45],
			"rotation": {"angle": -22.5, "axis": "x", "origin": [-8.125, 4.35, -2.375]},
			"faces": {
				"east": {"uv": [12.44444, 15.15789, 16, 16], "rotation": 270, "texture": "#0"},
				"down": {"uv": [8, 15.15789, 12.44444, 16], "texture": "#0"}
			}
		},
		{
			"from": [0, 6.15, -1.56],
			"to": [1.25, 6.2, -1.435],
			"rotation": {"angle": 45, "axis": "x", "origin": [-8.125, 3.375, -1.875]},
			"faces": {
				"east": {"uv": [12.44444, 15.15789, 16, 16], "texture": "#0"},
				"south": {"uv": [8, 15.15789, 12.44444, 16], "texture": "#0"}
			}
		},
		{
			"from": [0, 5.44, -0.7275],
			"to": [1.25, 5.49, -0.6025],
			"rotation": {"angle": 22.5, "axis": "x", "origin": [-8.125, 2.65, -1.05]},
			"faces": {
				"east": {"uv": [12.44444, 15.15789, 16, 16], "rotation": 270, "texture": "#0"},
				"south": {"uv": [8, 15.15789, 12.44444, 16], "texture": "#0"}
			}
		},
		{
			"from": [0, 11.13, 0],
			"to": [1.25, 11.235, 0.35],
			"rotation": {"angle": 0, "axis": "y", "origin": [-8.125, 10.775, 3.125]},
			"faces": {
				"north": {"uv": [0, 0, 12.76429, 1.43459], "texture": "#0"},
				"east": {"uv": [12.44444, 0, 16, 0.84211], "texture": "#0"},
				"up": {"uv": [8, 0, 12.44444, 0.84211], "texture": "#0"}
			}
		},
		{
			"from": [0, 5.01, 0],
			"to": [1.25, 5.115, 0.36],
			"rotation": {"angle": 0, "axis": "y", "origin": [-8.125, 4.65, 3.125]},
			"faces": {
				"north": {"uv": [0, 0, 12.76429, 1.43459], "texture": "#0"},
				"east": {"uv": [12.44444, 15.15789, 16, 16], "texture": "#0"},
				"down": {"uv": [8, 15.15789, 12.44444, 16], "texture": "#0"}
			}
		}
	],
	"display": {
		"thirdperson_righthand": {
			"translation": [0, 3.75, 7.5]
		},
		"thirdperson_lefthand": {
			"translation": [0, 3.75, 7.5]
		},
		"fixed": {
			"translation": [0, 0, 8.5]
		}
	}
}